ocqv/__init__.py
ocqv/app.py
ocqv/cli.py
oots_cs_query_validator-0.2.5.dist-info/licenses/LICENCE
oots_cs_query_validator-0.2.5.dist-info/METADATA
oots_cs_query_validator-0.2.5.dist-info/WHEEL
oots_cs_query_validator-0.2.5.dist-info/entry_points.txt
oots_cs_query_validator-0.2.5.dist-info/top_level.txt
oots_cs_query_validator-0.2.5.dist-info/RECORD
