Metadata-Version: 2.4
Name: OOTS-CS-Query-Validator
Version: 0.2.5
Summary: A query validator for the Common Services of the Once-Only Technical System.
Author-email: "M.P. van de Weerd" <michael@parcifal.dev>
License-Expression: AGPL-3.0-only
Project-URL: Homepage, https://gitlab.com/parcifal/ocqv
Project-URL: Bug Tracker, https://gitlab.com/parcifal/ocqv/-/issues
Keywords: Single Digital Gateway,SDG,Once-Only Technical System,OOTS,Common Services,Evidence Broker,Data Services Directory,Semantic Repository
Classifier: Development Status :: 4 - Beta
Classifier: Environment :: Other Environment
Classifier: Intended Audience :: Developers
License-File: LICENCE
Requires-Dist: werkzeug
Requires-Dist: tomli
Provides-Extra: dev
Requires-Dist: lxml; extra == "dev"
Requires-Dist: pylint; extra == "dev"
Requires-Dist: pylint-gitlab; extra == "dev"
Requires-Dist: pytest; extra == "dev"
Requires-Dist: pytest-cov; extra == "dev"
Requires-Dist: coverage; extra == "dev"
Provides-Extra: prod
Requires-Dist: uwsgi; extra == "prod"
Dynamic: license-file
